actionstudio/__init__.py
actionstudio/cli.py
actionstudio-0.0.1.dist-info/licenses/LICENSE
actionstudio-0.0.1.dist-info/METADATA
actionstudio-0.0.1.dist-info/WHEEL
actionstudio-0.0.1.dist-info/entry_points.txt
actionstudio-0.0.1.dist-info/top_level.txt
actionstudio-0.0.1.dist-info/RECORD
