Metadata-Version: 2.4
Name: actionstudio
Version: 0.0.1
Summary: ActionStudio.ai CLI — placeholder alpha (delegates to pydera)
Author-email: Think2Action <support@actionstudio.ai>
License: Apache-2.0
Project-URL: Homepage, https://actionstudio.ai
Classifier: Development Status :: 3 - Alpha
Classifier: Intended Audience :: Developers
Classifier: Programming Language :: Python :: 3
Classifier: License :: OSI Approved :: Apache Software License
Classifier: Operating System :: OS Independent
Requires-Python: >=3.9
License-File: LICENSE
Requires-Dist: pydera>=0.0.1
Dynamic: license-file
